Metadata-Version: 2.1
Name: joker-diskcache
Version: 0.4.1
Summary: Primitive disk-backed cache, probably useful in web scraping
Home-page: https://github.com/frozflame/joker-diskcache
Author: anonym
Author-email: anonym@example.com
License: GNU General Public License (GPL)
Platform: UNKNOWN
Classifier: Programming Language :: Python
Classifier: Programming Language :: Python :: 3
Classifier: Programming Language :: Python :: 3.4
Classifier: Programming Language :: Python :: 3.5
Classifier: Programming Language :: Python :: 3.6
